easy_transformers/__init__.py
easy_transformers/__version__.py
easy_transformers/aws_utils.py
easy_transformers/constants.py
easy_transformers/convert_to_onnx.py
easy_transformers/loader.py
easy_transformers/loggers.py
easy_transformers-0.19.0.dist-info/LICENSE
easy_transformers-0.19.0.dist-info/METADATA
easy_transformers-0.19.0.dist-info/WHEEL
easy_transformers-0.19.0.dist-info/top_level.txt
easy_transformers-0.19.0.dist-info/RECORD
